pyaair/__init__.py
pyaair/airports.py
pyaair/flights.py
pyaair/utils.py
pyaair-0.0.0.dist-info/LICENSE
pyaair-0.0.0.dist-info/METADATA
pyaair-0.0.0.dist-info/WHEEL
pyaair-0.0.0.dist-info/top_level.txt
pyaair-0.0.0.dist-info/RECORD
