Metadata-Version: 2.1
Name: pyaair
Version: 0.0.0
Summary: American Airlines scraper in Python
Author-email: John Balvin <johnchristian@hotmail.es>
License: MIT
Project-URL: Homepage, https://github.com/johnbalvin/pyaair
Keywords: American airlines,aa,scraper,crawler
License-File: LICENSE
Requires-Dist: bs4
Requires-Dist: requests
